bt_lamp/__init__.py
bt_lamp/__main__.py
bt_lamp/lib.py
bt_lamp-1.0.7.dist-info/LICENSE
bt_lamp-1.0.7.dist-info/METADATA
bt_lamp-1.0.7.dist-info/WHEEL
bt_lamp-1.0.7.dist-info/top_level.txt
bt_lamp-1.0.7.dist-info/RECORD
