Metadata-Version: 2.1
Name: bt-lamp
Version: 1.0.7
Summary: Controll bluetooth lamp from python
Home-page: https://github.com/LVettel/bt_lamp
Author: LVettel
Author-email: larin230@gmail.com
Project-URL: Documentation, https://github.com/LVettel/bt_lamp
Keywords: bluetooth python lamp
Classifier: Programming Language :: Python :: 3.9
Classifier: License :: OSI Approved :: MIT License
Classifier: Operating System :: OS Independent
Requires-Python: >=3.9
License-File: LICENSE
Requires-Dist: crcmod >=1.7
Requires-Dist: bleson >=0.1.8
